{
  "id" : "extendedDate",
  "name" : "General date data point with an extended source",
  "businessDefinition" : "Data point with an extended document reference as source, a date without a time-zone represented by a LocalDate. The date has to comply with ISO-8601.",
  "validatedBy" : "org.dataland.datalandbackend.model.datapoints.standard.LocalDateDataPoint",
  "example" : {
    "value" : "2007-03-05",
    "dateFormat" : "YYYY-MM-DD",
    "quality" : "Reported",
    "comment" : "The value is reported by the company.",
    "dataSource" : {
      "page" : "5-7",
      "tagName" : "date",
      "fileName" : "AnnualReport2020.pdf",
      "fileReference" : "207c80dd75e923a88ff283d8bf97e346c735d2859e27bd702cf033feaef6de47"
    },
    "applicable" : true
  }
}